agent_sim/__init__.py
agent_sim/agent.py
behavior_sim/__init__.py
behavior_sim/IDM/__init__.py
behavior_sim/IDM/idm.py
behavior_sim/MOBIL/__init__.py
behavior_sim/MOBIL/mobil.py
commonroad_agent-1.2.0.dist-info/LICENSE
commonroad_agent-1.2.0.dist-info/METADATA
commonroad_agent-1.2.0.dist-info/WHEEL
commonroad_agent-1.2.0.dist-info/top_level.txt
commonroad_agent-1.2.0.dist-info/RECORD
