Metadata-Version: 2.1
Name: commonroad-agent
Version: 1.2.0
Summary: Agent simulation with behavior models for CommonRoad
Home-page: UNKNOWN
License: UNKNOWN
Platform: UNKNOWN
Classifier: Programming Language :: Python :: 3
Classifier: Operating System :: OS Independent
Requires-Python: >=3.6
